arize/__init__.py
arize/api/__init__.py
arize/api/api.py
arize/api/bounded_executor.py
arize/api/version.py
arize/api/casting/__init__.py
arize/api/casting/casting.py
arize/api/casting/errors.py
arize/logging/__init__.py
arize/logging/formatter.py
arize/logging/helpers.py
arize/proto/__init__.py
arize/proto/helpers.py
arize/proto/public_pb2.py
arize/utils/__init__.py
arize/utils/constants.py
arize/utils/errors.py
arize/utils/model_mapping.json
arize/utils/types.py
arize/utils/utils.py
arize_slim-0.1.1.dist-info/METADATA
arize_slim-0.1.1.dist-info/WHEEL
arize_slim-0.1.1.dist-info/licenses/LICENSE.md
arize_slim-0.1.1.dist-info/RECORD
