Metadata-Version: 2.3
Name: arize-slim
Version: 0.1.1
Summary: A helper library to interact with Arize AI APIs
Project-URL: Homepage, https://arize.com
Project-URL: Documentation, https://docs.arize.com/arize
Project-URL: Issues, https://github.com/Arize-ai/client_python/issues
Project-URL: Source, https://github.com/Arize-ai/client_python
Project-URL: Changelog, https://github.com/Arize-ai/client_python/blob/main/packages/arize-slim/CHANGELOG.md
Author-email: Arize AI <support@arize.com>
Maintainer-email: Arize AI <support@arize.com>
License: BSD
License-File: LICENSE.md
Keywords: Arize,Evaluations,Explainability,LLM,Monitoring,Observability,Tracing
Classifier: Development Status :: 5 - Production/Stable
Classifier: Intended Audience :: Developers
Classifier: Programming Language :: Python
Classifier: Programming Language :: Python :: 3.6
Classifier: Programming Language :: Python :: 3.7
Classifier: Programming Language :: Python :: 3.8
Classifier: Programming Language :: Python :: 3.9
Classifier: Programming Language :: Python :: 3.10
Classifier: Programming Language :: Python :: 3.11
Classifier: Programming Language :: Python :: 3.12
Classifier: Programming Language :: Python :: 3.13
Classifier: Topic :: Scientific/Engineering :: Artificial Intelligence
Classifier: Topic :: Software Development :: Libraries :: Python Modules
Classifier: Topic :: System :: Logging
Classifier: Topic :: System :: Monitoring
Requires-Python: >=3.6
Requires-Dist: googleapis-common-protos~=1.51
Requires-Dist: requests-futures==1.0.0
